{
  "project_info": {
    "project_number": "778646113271",
    "project_id": "sidequest-afe17",
    "storage_bucket": "sidequest-afe17.firebasestorage.app"
  },
  "client": [
    {
      "client_info": {
        "mobilesdk_app_id": "1:778646113271:android:50b62f39bf0462a3eefcf2",
        "android_client_info": {
          "package_name": "com.example.sidequest"
        }
      },
      "oauth_client": [
        {
          "client_id": "778646113271-amvfsp8acv47230ec3r95121hie5gbna.apps.googleusercontent.com",
          "client_type": 3
        }
      ],
      "api_key": [
        {
          "current_key": "AIzaSyAWl1lkoLcFtVhCj1rNyg8Ld334onMBsrA"
        }
      ],
      "services": {
        "appinvite_service": {
          "other_platform_oauth_client": [
            {
              "client_id": "778646113271-amvfsp8acv47230ec3r95121hie5gbna.apps.googleusercontent.com",
              "client_type": 3
            },
            {
              "client_id": "778646113271-h2li7ghr1lu4b3tfhtb39l1q3ee5nu49.apps.googleusercontent.com",
              "client_type": 2,
              "ios_info": {
                "bundle_id": "com.example.sidequest"
              }
            }
          ]
        }
      }
    }
  ],
  "configuration_version": "1"
}